// class version 52.0 (52)
// access flags 0x11
public final class types/mainBt {


  // access flags 0x9
  public static foo(Ltypes/types/Foo;)V
    LDC "Foooooooooo"
    INVOKESTATIC io/github/thelimepixel/bento/RunFunctionsKt.fakePrintln (Ljava/lang/String;)V
    RETURN
    MAXSTACK = 1
    MAXLOCALS = 1

  // access flags 0x9
  public static printBar(Ltypes/types/Bar;)V
    ALOAD 0
    INVOKEVIRTUAL types/types/Bar.getName ()Ljava/lang/String;
    ASTORE 1
    ALOAD 1
    INVOKESTATIC io/github/thelimepixel/bento/RunFunctionsKt.fakePrintln (Ljava/lang/String;)V
    RETURN
    MAXSTACK = 1
    MAXLOCALS = 2

  // access flags 0x9
  public static main()V
    GETSTATIC types/types/Foo.INSTANCE : Ltypes/types/Foo;
    INVOKESTATIC types/mainBt.foo (Ltypes/types/Foo;)V
    NEW types/types/Bar
    DUP
    LDC "Bar"
    INVOKESPECIAL types/types/Bar.<init> (Ljava/lang/String;)V
    ASTORE 0
    ALOAD 0
    INVOKESTATIC types/mainBt.printBar (Ltypes/types/Bar;)V
    ALOAD 0
    LDC "Baz"
    INVOKEVIRTUAL types/types/Bar.setName (Ljava/lang/String;)V
    ALOAD 0
    INVOKESTATIC types/mainBt.printBar (Ltypes/types/Bar;)V
    RETURN
    MAXSTACK = 3
    MAXLOCALS = 1
}